PyDSWS/__init__.py
PyDSWS/datastream.py
PyDSWS-0.9.dist-info/METADATA
PyDSWS-0.9.dist-info/WHEEL
PyDSWS-0.9.dist-info/top_level.txt
PyDSWS-0.9.dist-info/RECORD
